cuemap/__init__.py
cuemap/client.py
cuemap/exceptions.py
cuemap/grounding.py
cuemap/models.py
cuemap-0.6.2.dist-info/licenses/LICENSE
cuemap-0.6.2.dist-info/METADATA
cuemap-0.6.2.dist-info/WHEEL
cuemap-0.6.2.dist-info/top_level.txt
cuemap-0.6.2.dist-info/RECORD
