Metadata-Version: 2.4
Name: cuemap
Version: 0.6.2
Summary: CueMap Python SDK - High-performance temporal-associative memory
Author-email: CueMap Team <hello@cuemap.dev>
License: MIT
Project-URL: Homepage, https://github.com/cuemap-dev/sdks
Project-URL: Documentation, https://github.com/cuemap-dev/sdks/blob/main/python/README.md
Project-URL: Repository, https://github.com/cuemap-dev/sdks
Project-URL: Issues, https://github.com/cuemap-dev/sdks/issues
Project-URL: Engine, https://github.com/cuemap-dev/engine
Keywords: ai,memory,agents,temporal,associative,llm,rag
Classifier: Development Status :: 4 - Beta
Classifier: Intended Audience :: Developers
Classifier: License :: OSI Approved :: MIT License
Classifier: Programming Language :: Python :: 3
Classifier: Programming Language :: Python :: 3.8
Classifier: Programming Language :: Python :: 3.9
Classifier: Programming Language :: Python :: 3.10
Classifier: Programming Language :: Python :: 3.11
Classifier: Programming Language :: Python :: 3.12
Classifier: Topic :: Software Development :: Libraries :: Python Modules
Classifier: Topic :: Scientific/Engineering :: Artificial Intelligence
Requires-Python: >=3.8
License-File: LICENSE
Requires-Dist: httpx>=0.25.0
Requires-Dist: pydantic>=2.0.0
Provides-Extra: dev
Requires-Dist: pytest>=7.0.0; extra == "dev"
Requires-Dist: pytest-asyncio>=0.21.0; extra == "dev"
Requires-Dist: build>=1.0.0; extra == "dev"
Requires-Dist: twine>=4.0.0; extra == "dev"
Dynamic: license-file
